rlutils/VERSION.txt
rlutils/__init__.py
rlutils/check_dependencies.py
rlutils/logx.py
rlutils/plot.py
rlutils/requirements.txt
rlutils/run.py
rlutils/algos/__init__.py
rlutils/algos/pytorch/__init__.py
rlutils/algos/pytorch/mf/__init__.py
rlutils/algos/pytorch/mf/sac.py
rlutils/algos/pytorch/mf/td3.py
rlutils/algos/tf/__init__.py
rlutils/algos/tf/mb/__init__.py
rlutils/algos/tf/mb/pets.py
rlutils/algos/tf/mf/__init__.py
rlutils/algos/tf/mf/ddpg.py
rlutils/algos/tf/mf/dqn.py
rlutils/algos/tf/mf/ppo.py
rlutils/algos/tf/mf/sac.py
rlutils/algos/tf/mf/td3.py
rlutils/algos/tf/mf/trpo.py
rlutils/algos/tf/mf/images/__init__.py
rlutils/algos/tf/mf/images/c51.py
rlutils/algos/tf/mf/images/dqn.py
rlutils/algos/tf/offline/__init__.py
rlutils/algos/tf/offline/bracp.py
rlutils/algos/tf/offline/cql.py
rlutils/algos/tf/offline/plas.py
rlutils/gym/__init__.py
rlutils/gym/utils.py
rlutils/gym/envs/__init__.py
rlutils/gym/envs/reset_obs/__init__.py
rlutils/gym/envs/reset_obs/ant.py
rlutils/gym/envs/reset_obs/half_cheetah.py
rlutils/gym/envs/reset_obs/hopper.py
rlutils/gym/envs/reset_obs/inverted_pendulum.py
rlutils/gym/envs/reset_obs/pendulum.py
rlutils/gym/envs/reset_obs/swimmer.py
rlutils/gym/envs/reset_obs/walker2d.py
rlutils/gym/envs/truncated/__init__.py
rlutils/gym/envs/truncated/ant_truncated.py
rlutils/gym/envs/truncated/humanoid_truncated.py
rlutils/gym/static/__init__.py
rlutils/gym/static/base.py
rlutils/gym/static/classic.py
rlutils/gym/static/mujoco.py
rlutils/gym/static/pybullet.py
rlutils/gym/vector/__init__.py
rlutils/gym/vector/async_vector_env.py
rlutils/gym/vector/sync_vector_env.py
rlutils/gym/vector/vector_env.py
rlutils/gym/wrappers/__init__.py
rlutils/gym/wrappers/transform_obs_dtype.py
rlutils/infra/__init__.py
rlutils/infra/seeder.py
rlutils/infra/tester.py
rlutils/infra/timer.py
rlutils/infra/updater.py
rlutils/infra/runner/__init__.py
rlutils/infra/runner/base.py
rlutils/infra/runner/commandline_utils.py
rlutils/infra/runner/pytorch_runner.py
rlutils_python-0.0.3.dist-info/LICENSE
rlutils_python-0.0.3.dist-info/METADATA
rlutils_python-0.0.3.dist-info/WHEEL
rlutils_python-0.0.3.dist-info/entry_points.txt
rlutils_python-0.0.3.dist-info/top_level.txt
rlutils_python-0.0.3.dist-info/RECORD
