Metadata-Version: 2.1
Name: rlutils-python
Version: 0.0.3
Summary: Reinforcement Learning Utilities
Home-page: https://github.com/vermouth1992/rlutils
Author: Chi Zhang
Author-email: czhangseu@gmail.com
License: Apache 2.0
Platform: UNKNOWN
